{
  "Questions": [
    {
      "Question": "Што е потребно за да се создаде звук?",
      "OptionA": "Мирување на предметот.",
      "OptionB": "Вибрација или треперење на некое тело.",
      "OptionC": "Само присуство на светлина.",
      "OptionD": "Вакуумски простор.",
      "CorrectAnswer": "OptionB"
    },
    {
      "Question": "Како се движат предметите кога вибрираат?",
      "OptionA": "Се движат многу брзо напред-назад.",
      "OptionB": "Се движат само во еден правец засекогаш.",
      "OptionC": "Се зголемуваат во големина.",
      "OptionD": "Стануваат невидливи.",
      "CorrectAnswer": "OptionA"
    },
    {
      "Question": "Кој орган ни овозможува да го слушнеме звукот?",
      "OptionA": "Окото",
      "OptionB": "Јазикот",
      "OptionC": "Увото",
      "OptionD": "Носот",
      "CorrectAnswer": "OptionC"
    },
    {
      "Question": "Што се случува кога ќе ја допрете звучната кутија на звучникот додека работи?",
      "OptionA": "Ќе почувствувате топлина.",
      "OptionB": "Ништо нема да почувствувате.",
      "OptionC": "Ќе почувствувате како таа се лади.",
      "OptionD": "Ќе почувствувате вибрации.",
      "CorrectAnswer": "OptionD"
    },
    {
      "Question": "Звукот патува низ воздухот во форма на:",
      "OptionA": "Звучни бранови.",
      "OptionB": "Електрични искри.",
      "OptionC": "Мали честички прашина.",
      "OptionD": "Светлински зраци.",
      "CorrectAnswer": "OptionA"
    },
    {
      "Question": "Низ кој материјал звукот патува најбрзо?",
      "OptionA": "Воздух",
      "OptionB": "Вода",
      "OptionC": "Железо (цврста материја)",
      "OptionD": "Масло",
      "CorrectAnswer": "OptionC"
    },
    {
      "Question": "Дали звукот може да патува низ течности?",
      "OptionA": "Не, само низ гасови.",
      "OptionB": "Да, звукот се пренесува низ течности.",
      "OptionC": "Само ако водата е топла.",
      "OptionD": "Само ако водата е солена.",
      "CorrectAnswer": "OptionB"
    },
    {
      "Question": "Зошто не можеме да слушнеме звук во вселената (вакуум)?",
      "OptionA": "Бидејќи таму е премногу ладно.",
      "OptionB": "Бидејќи нема материја (воздух) низ која би патувале вибрациите.",
      "OptionC": "Бидејќи таму нема сонце.",
      "OptionD": "Бидејќи вибрациите таму се премногу брзи.",
      "CorrectAnswer": "OptionB"
    },
    {
      "Question": "Која карактеристика на звукот ни кажува дали тој е тивок или гласен?",
      "OptionA": "Висина",
      "OptionB": "Јачина",
      "OptionC": "Боја",
      "OptionD": "Брзина",
      "CorrectAnswer": "OptionB"
    },
    {
      "Question": "Мерната единица за јачина на звукот е:",
      "OptionA": "Сентитеми (cm)",
      "OptionB": "Килoграми (kg)",
      "OptionC": "Литри (l)",
      "OptionD": "Децибели (dB)",
      "CorrectAnswer": "OptionD"
    },
    {
      "Question": "Што е висина на звукот?",
      "OptionA": "Колку децибели има звукот.",
      "OptionB": "Дали звукот е низок или висок.",
      "OptionC": "Колку далеку патува звукот.",
      "OptionD": "Колку долго трае звукот.",
      "CorrectAnswer": "OptionB"
    },
    {
      "Question": "Каков звук произведуваат предметите што вибрираат многу брзо?",
      "OptionA": "Низок звук",
      "OptionB": "Висок звук",
      "OptionC": "Тивок звук",
      "OptionD": "Никаков звук",
      "CorrectAnswer": "OptionB"
    },
    {
      "Question": "Тенките жици на музичките инструменти произведуваат:",
      "OptionA": "Повисок звук од дебелите жици.",
      "OptionB": "Понизок звук од дебелите жици.",
      "OptionC": "Ист звук како дебелите жици.",
      "OptionD": "Само тивок звук.",
      "CorrectAnswer": "OptionA"
    },
    {
      "Question": "Што се случува со висината на звукот кај дувачките инструменти ако воздушниот столб е подолг?",
      "OptionA": "Звукот станува повисок.",
      "OptionB": "Звукот станува погласен.",
      "OptionC": "Звукот станува понизок.",
      "OptionD": "Звукот не се менува.",
      "CorrectAnswer": "OptionC"
    },
    {
      "Question": "Кој материјал е добар за звучна изолација?",
      "OptionA": "Метал",
      "OptionB": "Стакло",
      "OptionC": "Бетон",
      "OptionD": "Сунѓер",
      "CorrectAnswer": "OptionD"
    },
    {
      "Question": "Што е ехо?",
      "OptionA": "Звук што се создава во вакуум.",
      "OptionB": "Одбивање на звучните бранови од некоја површина.",
      "OptionC": "Инструмент за мерење на бука.",
      "OptionD": "Вид на висока фреквенција.",
      "CorrectAnswer": "OptionB"
    },
    {
      "Question": "Кој од наведениве звуци е најгласен?",
      "OptionA": "Шепотење",
      "OptionB": "Нормален говор",
      "OptionC": "Полетување на авион",
      "OptionD": "Дождот што паѓа",
      "CorrectAnswer": "OptionC"
    },
    {
      "Question": "Како буката влијае врз нашето здравје?",
      "OptionA": "Го подобрува сонот.",
      "OptionB": "Нема никакво влијание.",
      "OptionC": "Може да предизвика вознемиреност и оштетување на слухот.",
      "OptionD": "Ја зголемува концентрацијата.",
      "CorrectAnswer": "OptionC"
    },
    {
      "Question": "Што користиме за да ги заштитиме ушите од многу силна бука?",
      "OptionA": "Очила",
      "OptionB": "Заштитни слушалки или тампони",
      "OptionC": "Ракавици",
      "OptionD": "Капа",
      "CorrectAnswer": "OptionB"
    },
    {
      "Question": "Кога велиме дека еден звук е „низок“, мислиме на неговата:",
      "OptionA": "Јачина",
      "OptionB": "Должина",
      "OptionC": "Брзина",
      "OptionD": "Висина",
      "CorrectAnswer": "OptionD"
    },
    {
      "Question": "Што се случува со звукот кога ќе се оддалечиме од изворот?",
      "OptionA": "Станува погласен.",
      "OptionB": "Станува постивок.",
      "OptionC": "Станува повисок.",
      "OptionD": "Станува понизок.",
      "CorrectAnswer": "OptionB"
    },
    {
      "Question": "Што вибрира кога зборуваме?",
      "OptionA": "Нашите заби.",
      "OptionB": "Нашиот јазик.",
      "OptionC": "Гласните жици во грлото.",
      "OptionD": "Нашите уши.",
      "CorrectAnswer": "OptionC"
    },
    {
      "Question": "Како се пренесува звукот низ цврсти предмети во споредба со воздухот?",
      "OptionA": "Побавно",
      "OptionB": "Исто брзо",
      "OptionC": "Побрзо и појасно",
      "OptionD": "Воопшто не се пренесува",
      "CorrectAnswer": "OptionC"
    },
    {
      "Question": "Кои животни користат ехолокација за да се движат?",
      "OptionA": "Лавовите",
      "OptionB": "Лилјаците",
      "OptionC": "Коњите",
      "OptionD": "Пчелите",
      "CorrectAnswer": "OptionB"
    },
    {
      "Question": "Што е тоа фреквенција на звукот?",
      "OptionA": "Јачината во децибели.",
      "OptionB": "Број на вибрации во една секунда.",
      "OptionC": "Бојата на гласот.",
      "OptionD": "Растојанието до каде се слуша звукот.",
      "CorrectAnswer": "OptionB"
    },
    {
      "Question": "Која е границата на звук по која тој станува болен за човечкото уво?",
      "OptionA": "Околу 20 dB",
      "OptionB": "Околу 120-130 dB",
      "OptionC": "Околу 60 dB",
      "OptionD": "Околу 5 dB",
      "CorrectAnswer": "OptionB"
    },
    {
      "Question": "При посилен удар на тапанот, звукот ќе биде:",
      "OptionA": "Понизок",
      "OptionB": "Потивок",
      "OptionC": "Погласен",
      "OptionD": "Повисок",
      "CorrectAnswer": "OptionC"
    },
    {
      "Question": "Кој инструмент произведува звук со вибрирање на воздушен столб?",
      "OptionA": "Гитара",
      "OptionB": "Флејта",
      "OptionC": "Пијано",
      "OptionD": "Тапани",
      "CorrectAnswer": "OptionB"
    },
    {
      "Question": "Зошто музичките сали имаат завеси и меки облоги на ѕидовите?",
      "OptionA": "За да изгледаат поубаво.",
      "OptionB": "За да го впијат звукот и да спречат ехо.",
      "OptionC": "За да ја загреат просторијата.",
      "OptionD": "За да го засилат звукот.",
      "CorrectAnswer": "OptionB"
    },
    {
      "Question": "Како се вика апаратот со кој може да се види изгледот на звучниот бран?",
      "OptionA": "Микроскоп",
      "OptionB": "Телескоп",
      "OptionC": "Осцилоскоп",
      "OptionD": "Термометар",
      "CorrectAnswer": "OptionC"
    },
    {
      "Question": "Ако ја затегнеме жицата на гитарата уште повеќе, звукот ќе биде:",
      "OptionA": "Повисок",
      "OptionB": "Понизок",
      "OptionC": "Потивок",
      "OptionD": "Нема да се промени",
      "CorrectAnswer": "OptionA"
    },
    {
      "Question": "Што се случува кога звучните бранови ќе стигнат до нашето ушно тапанче?",
      "OptionA": "Тапанчето се загрева.",
      "OptionB": "Тапанчето почнува да вибрира.",
      "OptionC": "Тапанчето се шири.",
      "OptionD": "Тапанчето се топи.",
      "CorrectAnswer": "OptionB"
    },
    {
      "Question": "Кој звук е попријатен за човечкото уво?",
      "OptionA": "Силна експлозија",
      "OptionB": "Тивка класична музика",
      "OptionC": "Крикот на сирена",
      "OptionD": "Ударен чекан на улица",
      "CorrectAnswer": "OptionB"
    },
    {
      "Question": "Како се движат честичките на воздухот кога звукот патува низ него?",
      "OptionA": "Летаат во еден правец без враќање.",
      "OptionB": "Вибрираат пренесувајќи ја енергијата на соседните честички.",
      "OptionC": "Се претвораат во течност.",
      "OptionD": "Се палат.",
      "CorrectAnswer": "OptionB"
    },
    {
      "Question": "Кој инструмент е ударен инструмент?",
      "OptionA": "Виолина",
      "OptionB": "Труба",
      "OptionC": "Чинели",
      "OptionD": "Кларинет",
      "CorrectAnswer": "OptionC"
    },
    {
      "Question": "Што е децибелометар?",
      "OptionA": "Уред за мерење на висината на звукот.",
      "OptionB": "Уред за мерење на јачината на звукот.",
      "OptionC": "Уред за мерење на брзината на ветерот.",
      "OptionD": "Уред за слушање на далечни звуци.",
      "CorrectAnswer": "OptionB"
    },
    {
      "Question": "Звукот кој го создава пчелата со крилјата е:",
      "OptionA": "Многу низок звук.",
      "OptionB": "Висок звук поради брзите вибрации.",
      "OptionC": "Звук кој не се слуша.",
      "OptionD": "Електричен звук.",
      "CorrectAnswer": "OptionB"
    },
    {
      "Question": "Што се случува во увото по вибрирањето на тапанчето?",
      "OptionA": "Сигналот се пренесува до мозокот преку нерви.",
      "OptionB": "Сигналот се брише.",
      "OptionC": "Се создава светлина.",
      "OptionD": "Увото почнува да свети.",
      "CorrectAnswer": "OptionA"
    },
    {
      "Question": "Каков звук испушта големо животно како слон?",
      "OptionA": "Многу висок и пискав.",
      "OptionB": "Низок и длабок звук.",
      "OptionC": "Звук со висока фреквенција.",
      "OptionD": "Само нечуен звук.",
      "CorrectAnswer": "OptionB"
    },
    {
      "Question": "Зошто во празна просторија звукот има повеќе ехо?",
      "OptionA": "Бидејќи има повеќе воздух.",
      "OptionB": "Бидејќи нема меки предмети што би го впиле звукот.",
      "OptionC": "Бидејќи е темно.",
      "OptionD": "Бидејќи ѕидовите се подебели.",
      "CorrectAnswer": "OptionB"
    },
    {
      "Question": "Која е најниската јачина на звук што човекот може да ја слушне?",
      "OptionA": "0 dB (праг на чујност)",
      "OptionB": "50 dB",
      "OptionC": "100 dB",
      "OptionD": "-50 dB",
      "CorrectAnswer": "OptionA"
    },
    {
      "Question": "Колку е погуста материјата низ која патува звукот, толку тој патува:",
      "OptionA": "Побавно",
      "OptionB": "Побрзо",
      "OptionC": "Исто",
      "OptionD": "Воопшто не патува",
      "CorrectAnswer": "OptionB"
    },
    {
      "Question": "Што се случува со звукот кога ќе наиде на мека препрека како памук?",
      "OptionA": "Се одбива многу силно.",
      "OptionB": "Се впива (апсорбира).",
      "OptionC": "Се забрзува.",
      "OptionD": "Ја менува висината.",
      "CorrectAnswer": "OptionB"
    },
    {
      "Question": "Вибрациите кај гитарата се пренесуваат од жицата на:",
      "OptionA": "Раката на свирачот.",
      "OptionB": "Воздухот во звучната кутија.",
      "OptionC": "Сонцето.",
      "OptionD": "Земјата.",
      "CorrectAnswer": "OptionB"
    },
    {
      "Question": "Што е бука во училницата?",
      "OptionA": "Тишината додека се пишува тест.",
      "OptionB": "Гласното зборување на сите одеднаш.",
      "OptionC": "Мирисот на боичките.",
      "OptionD": "Бојата на ѕидовите.",
      "CorrectAnswer": "OptionB"
    },
    {
      "Question": "При вриење на водата, звукот настанува од:",
      "OptionA": "Движењето на меурчињата и нивното пукање.",
      "OptionB": "Бојата на водата.",
      "OptionC": "Тежината на садот.",
      "OptionD": "Светлината во кујната.",
      "CorrectAnswer": "OptionA"
    },
    {
      "Question": "Која е главната разлика помеѓу музика и бука?",
      "OptionA": "Музиката секогаш е тивка.",
      "OptionB": "Буката секогаш е убава.",
      "OptionC": "Музиката има правилни вибрации, а буката неправилни.",
      "OptionD": "Нема никаква разлика.",
      "CorrectAnswer": "OptionC"
    },
    {
      "Question": "Што се случува ако ја скратиме жицата на еден инструмент?",
      "OptionA": "Звукот станува повисок.",
      "OptionB": "Звукот станува понизок.",
      "OptionC": "Звукот исчезнува.",
      "OptionD": "Звукот станува потивок.",
      "CorrectAnswer": "OptionA"
    },
    {
      "Question": "Како се викаат научниците кои го проучуваат звукот?",
      "OptionA": "Биолози",
      "OptionB": "Акустичари",
      "OptionC": "Геолози",
      "OptionD": "Астрономи",
      "CorrectAnswer": "OptionB"
    },
    {
      "Question": "Кој звук нè предупредува на опасност?",
      "OptionA": "Песна на птица",
      "OptionB": "Сирена на брза помош",
      "OptionC": "Шумење на лисја",
      "OptionD": "Тропање на дожд",
      "CorrectAnswer": "OptionB"
    },
    {
      "Question": "Звукот е вид на:",
      "OptionA": "Материја",
      "OptionB": "Енергија",
      "OptionC": "Хемикалија",
      "OptionD": "Гас",
      "CorrectAnswer": "OptionB"
    },
    {
      "Question": "Што се случува кога ставаме тампони во ушите?",
      "OptionA": "Ја зголемуваме јачината на звукот.",
      "OptionB": "Го спречуваме патот на звучните бранови до тапанчето.",
      "OptionC": "Го правиме звукот повисок.",
      "OptionD": "Ги чистиме ушите.",
      "CorrectAnswer": "OptionB"
    },
    {
      "Question": "Кој од наведениве е извор на природен звук?",
      "OptionA": "Радио",
      "OptionB": "Грмотевица",
      "OptionC": "Автомобил",
      "OptionD": "Телевизор",
      "CorrectAnswer": "OptionB"
    },
    {
      "Question": "Зошто користиме микрофон?",
      "OptionA": "За да го направиме звукот повисок.",
      "OptionB": "За да ги претвориме звучните бранови во електричен сигнал и да ги засилиме.",
      "OptionC": "За да го изгасиме звукот.",
      "OptionD": "За да ја смениме бојата на гласот во зелена.",
      "CorrectAnswer": "OptionB"
    },
    {
      "Question": "Звукот од комарците е многу висок затоа што тие:",
      "OptionA": "Имаат големи крилја.",
      "OptionB": "Мавтаат со крилјата многу често (брзо вибрираат).",
      "OptionC": "Се многу тешки.",
      "OptionD": "Јадат многу шеќер.",
      "CorrectAnswer": "OptionB"
    },
    {
      "Question": "Што покажува „висока“ линија на осцилоскоп?",
      "OptionA": "Тивок звук",
      "OptionB": "Гласен звук (голема амплитуда)",
      "OptionC": "Низок звук",
      "OptionD": "Никаков звук",
      "CorrectAnswer": "OptionB"
    },
    {
      "Question": "Каде е најопасно да се слуша премногу гласна музика?",
      "OptionA": "Во парк",
      "OptionB": "Преку слушалки директно во ушите",
      "OptionC": "На телевизија",
      "OptionD": "Во другата соба",
      "CorrectAnswer": "OptionB"
    },
    {
      "Question": "Кој звук го нарекуваме „ултразвук“?",
      "OptionA": "Многу низок звук.",
      "OptionB": "Звук со многу висока фреквенција што луѓето не го слушаат.",
      "OptionC": "Многу тивок звук.",
      "OptionD": "Звук на музички инструмент.",
      "CorrectAnswer": "OptionB"
    },
    {
      "Question": "Што се случува кога два звучни бранови ќе се сретнат?",
      "OptionA": "Експлодираат.",
      "OptionB": "Се преклопуваат (интерференција).",
      "OptionC": "Исчезнуваат засекогаш.",
      "OptionD": "Стануваат цврсти.",
      "CorrectAnswer": "OptionB"
    },
    {
      "Question": "Која е основната порака за заштита на слухот?",
      "OptionA": "Слушајте што погласна музика.",
      "OptionB": "Избегнувајте места со силна бука и штитете ги ушите.",
      "OptionC": "Никогаш не мијте ги ушите.",
      "OptionD": "Зборувајте секогаш со викање.",
      "CorrectAnswer": "OptionB"
    }
  ]
}